datarunner/__init__.py
datarunner-1.2.5.dist-info/LICENSE
datarunner-1.2.5.dist-info/METADATA
datarunner-1.2.5.dist-info/WHEEL
datarunner-1.2.5.dist-info/top_level.txt
datarunner-1.2.5.dist-info/RECORD
