Metadata-Version: 2.1
Name: datarunner
Version: 1.2.5
Summary: A simple data workflow runner that helps you write better ETL scripts using reusable code pieces.
Home-page: https://github.com/maxzheng/datarunner
Author: Max Zheng
Author-email: maxzheng.os@gmail.com
License: MIT
Keywords: run call code workflow etl extract transform load
Platform: UNKNOWN
Classifier: Development Status :: 5 - Production/Stable
Classifier: Intended Audience :: Developers
Classifier: Topic :: Software Development :: Libraries :: Python Modules
Classifier: License :: OSI Approved :: MIT License
Classifier: Programming Language :: Python :: 3
Classifier: Programming Language :: Python :: 3.6
Classifier: Programming Language :: Python :: 3.7
Requires-Python: >=3.6
